SimpleITK/SimpleITK.py
SimpleITK/_SimpleITK.cpython-36m-darwin.so
SimpleITK/__init__.py
SimpleITK_Elastix-2.0.0rc2.data/data/ITK-5.1-NOTICE
SimpleITK_Elastix-2.0.0rc2.data/data/ITK-5.1-README.md
SimpleITK_Elastix-2.0.0rc2.data/data/LICENSE
SimpleITK_Elastix-2.0.0rc2.data/data/NOTICE
SimpleITK_Elastix-2.0.0rc2.data/data/README.md
SimpleITK_Elastix-2.0.0rc2.dist-info/METADATA
SimpleITK_Elastix-2.0.0rc2.dist-info/WHEEL
SimpleITK_Elastix-2.0.0rc2.dist-info/top_level.txt
SimpleITK_Elastix-2.0.0rc2.dist-info/RECORD
