Metadata-Version: 2.1
Name: SimpleITK-Elastix
Version: 2.0.0rc2
Summary: SimpleITK is a simplified interface to the Insight Toolkit (ITK) for image registration and segmentation
Home-page: http://simpleitk.org/
Author: Insight Software Consortium
Author-email: insight-users@itk.org
License: Apache
Download-URL: https://www.itk.org/SimpleITKDoxygen/html/PyDownloadPage.html
Keywords: SimpleITK ITK InsightToolkit segmentation registration
Platform: UNKNOWN
Classifier: License :: OSI Approved :: Apache Software License
Classifier: Programming Language :: Python
Classifier: Programming Language :: C++
Classifier: Development Status :: 5 - Production/Stable
Classifier: Intended Audience :: Education
Classifier: Intended Audience :: Healthcare Industry
Classifier: Intended Audience :: Science/Research
Classifier: Topic :: Scientific/Engineering
Classifier: Topic :: Scientific/Engineering :: Medical Science Apps.
Classifier: Topic :: Scientific/Engineering :: Information Analysis
Classifier: Topic :: Software Development :: Libraries
Classifier: Operating System :: Microsoft :: Windows
Classifier: Operating System :: POSIX
Classifier: Operating System :: Unix
Classifier: Operating System :: MacOS
